thunderpy/__init__.py
thunderpy/core.py
thunderpy/d.py
thunderpy/t.py
thunderpy-1.0.0.dist-info/METADATA
thunderpy-1.0.0.dist-info/WHEEL
thunderpy-1.0.0.dist-info/top_level.txt
thunderpy-1.0.0.dist-info/RECORD
