Metadata-Version: 2.4
Name: thunderpy
Version: 1.0.0
Summary: Testlibrarry
Author: whyraze
Requires-Python: >=3.6
Dynamic: author
Dynamic: requires-python
Dynamic: summary
